
  <dir>
    <title>1999 Movies</title>
    <tmdb>year/movies/1999</tmdb>
  </dir>

  <dir>
    <title>1998 Movies</title>
    <tmdb>year/movies/1998</tmdb>
  </dir>

  <dir>
    <title>1997 Movies</title>
    <tmdb>year/movies/1997</tmdb>
  </dir>

  <dir>
    <title>1996 Movies</title>
    <tmdb>year/movies/1996</tmdb>
  </dir>

  <dir>
    <title>1995 Movies</title>
    <tmdb>year/movies/1995</tmdb>
  </dir>

  <dir>
    <title>1994 Movies</title>
    <tmdb>year/movies/1994</tmdb>
  </dir>

  <dir>
    <title>1993 Movies</title>
    <tmdb>year/movies/1993</tmdb>
  </dir>

  <dir>
    <title>1992 Movies</title>
    <tmdb>year/movies/1992</tmdb>
  </dir>

  <dir>
    <title>1991 Movies</title>
    <tmdb>year/movies/1991</tmdb>
  </dir>

  <dir>
    <title>1990 Movies</title>
    <tmdb>year/movies/1990</tmdb>
  </dir>

  <dir>
    <title>1989 Movies</title>
    <tmdb>year/movies/1989</tmdb>
  </dir>

  <dir>
    <title>1988 Movies</title>
    <tmdb>year/movies/1988</tmdb>
  </dir>

  <dir>
    <title>1987 Movies</title>
    <tmdb>year/movies/1987</tmdb>
  </dir>

  <dir>
    <title>1986 Movies</title>
    <tmdb>year/movies/1986</tmdb>
  </dir>

  <dir>
    <title>1985 Movies</title>
    <tmdb>year/movies/1985</tmdb>
  </dir>

  <dir>
    <title>1984 Movies</title>
    <tmdb>year/movies/1984</tmdb>
  </dir>

  <dir>
    <title>1983 Movies</title>
    <tmdb>year/movies/1983</tmdb>
  </dir>

  <dir>
    <title>1982 Movies</title>
    <tmdb>year/movies/1982</tmdb>
  </dir>

  <dir>
    <title>1981 Movies</title>
    <tmdb>year/movies/1981</tmdb>
  </dir>

  <dir>
    <title>1980 Movies</title>
    <tmdb>year/movies/1980</tmdb>
  </dir>
